Metadata-Version: 1.0
Name: gbdc-probability
Version: 0.1
Summary: Gaussian distributions
Home-page: UNKNOWN
Author: Adeshola Afolabi
Author-email: UNKNOWN
License: UNKNOWN
Platform: UNKNOWN
